.gitattributes
.gitignore
.scrutinizer.yml
.sourcery.yaml
CHANGELOG.md
LICENSE
Peek.gif
README.md
TUIFI.png
flake.lock
flake.nix
noxfile.py
pyproject.toml
requirements.txt
setup.cfg
setup.py
.github/ISSUE_TEMPLATE/bug_report.md
.github/ISSUE_TEMPLATE/feature_request.md
.github/workflows/nox_ci.yml
TUIFIManager/TUIFIProfile.py
TUIFIManager/TUIFile.py
TUIFIManager/TUIMenu.py
TUIFIManager/TUIProps.py
TUIFIManager/TUISynthXDND.py
TUIFIManager/TUItilities.py
TUIFIManager/__init__.py
TUIFIManager/__main__.py
TUIFIManager.egg-info/PKG-INFO
TUIFIManager.egg-info/SOURCES.txt
TUIFIManager.egg-info/dependency_links.txt
TUIFIManager.egg-info/entry_points.txt
TUIFIManager.egg-info/requires.txt
TUIFIManager.egg-info/top_level.txt
etc/tuifi_cd.sh
etc/tuifi_cd_on_esc_termux.sh