Metadata-Version: 2.4
Name: TUIFIManager
Version: 5.2.5
Summary: A cross-platform terminal-based termux-oriented file manager.
Home-page: https://github.com/GiorgosXou/TUIFIManager
Author: George Chousos
Author-email: George Chousos <gxousos@gmail.com>
License: General Public License v3.0
Project-URL: Github, https://github.com/GiorgosXou/TUIFIManager
Keywords: file-manager,terminal,tui,ncurses,pdcurses,uni-curses,termux,vim,vim-motions,cross-platform
Platform: unix
Platform: linux
Platform: osx
Platform: cygwin
Platform: windows
Classifier: Intended Audience :: Developers
Classifier: Intended Audience :: End Users/Desktop
Classifier: License :: OSI Approved :: MIT License
Classifier: Operating System :: MacOS :: MacOS X
Classifier: Operating System :: Microsoft :: Windows
Classifier: Operating System :: POSIX
Classifier: Programming Language :: Python :: 3 :: Only
Classifier: Programming Language :: Python :: 3.8
Classifier: Programming Language :: Python :: 3.9
Classifier: Programming Language :: Python :: 3.10
Requires-Python: >=3.8
License-File: LICENSE
Requires-Dist: uni-curses>=3.1.2
Requires-Dist: Send2Trash>=1.8.0
Dynamic: license-file
